topotem_test/__init__.py
topotem_test-0.1.0.dist-info/METADATA
topotem_test-0.1.0.dist-info/WHEEL
topotem_test-0.1.0.dist-info/RECORD
