Metadata-Version: 2.1
Name: topotem-test
Version: 0.1.0
Summary: 
Author: GeriTopore
Author-email: geritopore@gmail.com
Requires-Python: >=3.8,<4.0
Classifier: Programming Language :: Python :: 3
Classifier: Programming Language :: Python :: 3.8
Classifier: Programming Language :: Python :: 3.9
Classifier: Programming Language :: Python :: 3.10
Classifier: Programming Language :: Python :: 3.11
Requires-Dist: atomap (>=0.3.3,<0.4.0)
Requires-Dist: hyperspy (>=1.7.5,<2.0.0)
Requires-Dist: matplotlib-scalebar (>=0.8.1,<0.9.0)
